loky/__init__.py
loky/_base.py
loky/cloudpickle_wrapper.py
loky/initializers.py
loky/process_executor.py
loky/reusable_executor.py
loky/backend/__init__.py
loky/backend/_posix_reduction.py
loky/backend/_win_reduction.py
loky/backend/context.py
loky/backend/fork_exec.py
loky/backend/popen_loky_posix.py
loky/backend/popen_loky_win32.py
loky/backend/process.py
loky/backend/queues.py
loky/backend/reduction.py
loky/backend/resource_tracker.py
loky/backend/spawn.py
loky/backend/synchronize.py
loky/backend/utils.py
loky-3.5.3.dist-info/licenses/LICENSE.txt
loky-3.5.3.dist-info/METADATA
loky-3.5.3.dist-info/WHEEL
loky-3.5.3.dist-info/top_level.txt
loky-3.5.3.dist-info/RECORD
