Metadata-Version: 2.4
Name: loky
Version: 3.5.3
Summary: A robust implementation of concurrent.futures.ProcessPoolExecutor
Author-email: Thomas Moreau <thomas.moreau.2010@gmail.com>
License: BSD 3-Clause License
Project-URL: Homepage, http://loky.readthedocs.io
Project-URL: Source, https://github.com/joblib/loky
Platform: any
Classifier: Development Status :: 5 - Production/Stable
Classifier: Environment :: Console
Classifier: Intended Audience :: Developers
Classifier: Intended Audience :: Science/Research
Classifier: License :: OSI Approved :: BSD License
Classifier: Operating System :: OS Independent
Classifier: Programming Language :: Python :: 3
Classifier: Programming Language :: Python :: 3.9
Classifier: Programming Language :: Python :: 3.10
Classifier: Programming Language :: Python :: 3.11
Classifier: Programming Language :: Python :: 3.12
Classifier: Programming Language :: Python :: 3.13
Classifier: Topic :: Scientific/Engineering
Classifier: Topic :: Utilities
Classifier: Topic :: Software Development :: Libraries
Requires-Python: >=3.9
License-File: LICENSE.txt
Requires-Dist: cloudpickle
Provides-Extra: tests
Requires-Dist: packaging; extra == "tests"
Requires-Dist: pytest; extra == "tests"
Requires-Dist: psutil; extra == "tests"
Dynamic: license-file
